restaurant_preprocessing/__init__.py
restaurant_preprocessing/preprocessing.py
restaurant_preprocessing/version_util.py
remla23_team10_preprocessing-2.0.1.dist-info/LICENSE
remla23_team10_preprocessing-2.0.1.dist-info/METADATA
remla23_team10_preprocessing-2.0.1.dist-info/WHEEL
remla23_team10_preprocessing-2.0.1.dist-info/top_level.txt
remla23_team10_preprocessing-2.0.1.dist-info/RECORD
